<annotation><folder>potholes</folder><filename>214.jpg</filename><size><width>640</width><height>360</height><depth>3</depth></size><object><name>pothole</name><pose>Unspecified</pose><truncated>0</truncated><difficult>0</difficult><confidence>0.899</confidence><bndbox><xmin>263</xmin><ymin>227</ymin><xmax>509</xmax><ymax>321</ymax></bndbox></object><object><name>pothole</name><pose>Unspecified</pose><truncated>0</truncated><difficult>0</difficult><confidence>0.896</confidence><bndbox><xmin>217</xmin><ymin>170</ymin><xmax>404</xmax><ymax>221</ymax></bndbox></object><object><name>pothole</name><pose>Unspecified</pose><truncated>0</truncated><difficult>0</difficult><confidence>0.580</confidence><bndbox><xmin>161</xmin><ymin>95</ymin><xmax>259</xmax><ymax>130</ymax></bndbox></object><object><name>pothole</name><pose>Unspecified</pose><truncated>0</truncated><difficult>0</difficult><confidence>0.355</confidence><bndbox><xmin>170</xmin><ymin>66</ymin><xmax>237</xmax><ymax>82</ymax></bndbox></object><object><name>pothole</name><pose>Unspecified</pose><truncated>0</truncated><difficult>0</difficult><confidence>0.318</confidence><bndbox><xmin>174</xmin><ymin>50</ymin><xmax>223</xmax><ymax>62</ymax></bndbox></object><object><name>pothole</name><pose>Unspecified</pose><truncated>0</truncated><difficult>0</difficult><confidence>0.280</confidence><bndbox><xmin>165</xmin><ymin>61</ymin><xmax>243</xmax><ymax>83</ymax></bndbox></object></annotation>